tests/__init__.py
tests/test_directory_monitor.py
tests/test_file_operations.py
tests/test_image_operations.py
tests/test_json_operations.py
tests/test_llm_image_operations.py
utility_lib/__init__.py
utility_lib/common/__init__.py
utility_lib/common/directory_operations.py
utility_lib/common/file_operations.py
utility_lib/common/image_operations.py
utility_lib/common/json_operations.py
utility_lib/llm/__init__.py
utility_lib/llm/llm_image_operation.py
optimized_utility_library-0.1.3.dist-info/METADATA
optimized_utility_library-0.1.3.dist-info/WHEEL
optimized_utility_library-0.1.3.dist-info/top_level.txt
optimized_utility_library-0.1.3.dist-info/RECORD
